{"#Panel_skill#Node_cell_7":{"width":0,"height":0,"visible":1,"offsetx":0,"offsety":0},"#Panel_skill#Node_cell_6":{"width":0,"height":0,"visible":1,"offsetx":0,"offsety":0},"#Button_pick":{"width":59,"height":59,"visible":0,"offsetx":0,"offsety":0},"#Button_Lock":{"width":59,"height":59,"visible":0,"offsetx":0,"offsety":0},"#Panel_skill#Button_attack":{"width":58,"height":58,"visible":1,"offsetx":0,"offsety":0},"#Panel_skill#Panel_quick_find#Image_hero":{"width":60,"height":60,"visible":0,"offsetx":0,"offsety":0},"#Panel_skill#Node_cell_4":{"width":0,"height":0,"visible":1,"offsetx":0,"offsety":0},"#Panel_button#Panel_constant#Button_change":{"width":62,"height":62,"visible":1,"offsetx":0,"offsety":0},"#Panel_skill#Node_cell_1":{"width":0,"height":0,"visible":1,"offsetx":0,"offsety":0},"#Panel_skill#Panel_quick_find":{"width":120,"height":120,"visible":1,"offsetx":0,"offsety":0},"#Panel_skill#Node_cell_9":{"width":0,"height":0,"visible":1,"offsetx":0,"offsety":0},"#Panel_skill#Node_cell_3":{"width":0,"height":0,"visible":1,"offsetx":0,"offsety":0},"#Panel_skill#Panel_quick_find#Image_player":{"width":53,"height":48,"visible":1,"offsetx":0,"offsety":0},"#Node_hj_skill":{"width":0,"height":0,"visible":1,"offsetx":0,"offsety":0},"#Panel_skill#Node_cell_5":{"width":0,"height":0,"visible":1,"offsetx":0,"offsety":0},"#Panel_skill#Node_cell_2":{"width":0,"height":0,"visible":1,"offsetx":0,"offsety":0}}